trex/README.md
trex/__init__.py
trex/activations.py
trex/compare_engines.py
trex/df_preprocessing.py
trex/engine_plan.py
trex/excel_summary.py
trex/graphing.py
trex/interactive.py
trex/layer.py
trex/lint.py
trex/misc.py
trex/notebook.py
trex/parser.py
trex/plotting.py
trex/raw_preprocessing.py
trex/report_card.py
trt_engine_explorer-0.1.5.dist-info/METADATA
trt_engine_explorer-0.1.5.dist-info/WHEEL
trt_engine_explorer-0.1.5.dist-info/RECORD
