Metadata-Version: 2.1
Name: trt-engine-explorer
Version: 0.1.5
Summary: NVIDIA's experimental tool to explore TRT engines
Home-page: https://github.com/NVIDIA/TensorRT/tree/release/8.6/tools/experimental/trt-engine-explorer
License: Apache-2.0
Author: Silky Arora
Author-email: silky.arora@flyzipline.com
Requires-Python: >=3.8,<4.0
Classifier: License :: OSI Approved :: Apache Software License
Classifier: Programming Language :: Python :: 3
Classifier: Programming Language :: Python :: 3.8
Classifier: Programming Language :: Python :: 3.9
Classifier: Programming Language :: Python :: 3.10
Classifier: Programming Language :: Python :: 3.11
Classifier: Programming Language :: Python :: 3.12
Requires-Dist: dtale (>=2.2.0,<3.0.0)
Requires-Dist: flask (==2.1.2)
Requires-Dist: graphviz (>=0.20.1,<0.21.0)
Requires-Dist: ipyfilechooser (>=0.6.0,<0.7.0)
Requires-Dist: ipywidgets (==8.0.2)
Requires-Dist: jupyter (>=1.0.0,<2.0.0)
Requires-Dist: jupyter-dash (>=0.4.2,<0.5.0)
Requires-Dist: jupyterlab (>=3.4.3,<4.0.0)
Requires-Dist: kaleido (==0.2.1)
Requires-Dist: netron (>=7.2.8,<8.0.0)
Requires-Dist: numpy (>=1.24.3,<2.0.0)
Requires-Dist: onnx (>=1.12.0,<2.0.0)
Requires-Dist: openpyxl (>=3.1.2,<4.0.0)
Requires-Dist: pandas (>=1.5.3,<2.0.0)
Requires-Dist: plotly (>=5.18.0,<6.0.0)
Requires-Dist: protobuf (>=3.20.0,<4.0.0)
Requires-Dist: pytest (>=6.2.5,<7.0.0)
Requires-Dist: qgrid (>=1.3.1,<2.0.0)
Requires-Dist: setuptools (>=68.2.2,<69.0.0)
Requires-Dist: traitlets (==5.9.0)
Requires-Dist: werkzeug (==2.0.1)
Requires-Dist: wheel (>=0.41.3,<0.42.0)
Requires-Dist: xlsxwriter (>=3.1.9,<4.0.0)
Project-URL: Repository, https://github.com/NVIDIA/TensorRT
